CHANGELOG.md
MANIFEST.in
README.rst
setup.cfg
setup.py
tailbone_harvest/__init__.py
tailbone_harvest/_version.py
tailbone_harvest/menus.py
tailbone_harvest.egg-info/PKG-INFO
tailbone_harvest.egg-info/SOURCES.txt
tailbone_harvest.egg-info/dependency_links.txt
tailbone_harvest.egg-info/requires.txt
tailbone_harvest.egg-info/top_level.txt
tailbone_harvest/static/__init__.py
tailbone_harvest/templates/harvest-util.mako
tailbone_harvest/templates/harvest/time-entries/view.mako
tailbone_harvest/templates/harvest/users/view.mako
tailbone_harvest/views/__init__.py
tailbone_harvest/views/harvest/__init__.py
tailbone_harvest/views/harvest/clients.py
tailbone_harvest/views/harvest/master.py
tailbone_harvest/views/harvest/projects.py
tailbone_harvest/views/harvest/tasks.py
tailbone_harvest/views/harvest/time_entries.py
tailbone_harvest/views/harvest/users.py